simple_gcp_object_downloader/'
simple_gcp_object_downloader/__init__.py
simple_gcp_object_downloader/download_gcp_object.py
simple_gcp_object_downloader-0.1.0.dist-info/entry_points.txt
simple_gcp_object_downloader-0.1.0.dist-info/LICENSE
simple_gcp_object_downloader-0.1.0.dist-info/WHEEL
simple_gcp_object_downloader-0.1.0.dist-info/METADATA
simple_gcp_object_downloader-0.1.0.dist-info/RECORD
