Metadata-Version: 2.1
Name: simple-gcp-object-downloader
Version: 0.1.0
Summary: 
Author: Jackie Tung
Author-email: jackie@outerbounds.co
Requires-Python: >=3.7,<4.0
Classifier: Programming Language :: Python :: 3
Classifier: Programming Language :: Python :: 3.10
Classifier: Programming Language :: Python :: 3.7
Classifier: Programming Language :: Python :: 3.8
Classifier: Programming Language :: Python :: 3.9
Requires-Dist: google-cloud-storage (>=2.4.0)
